absum/__init__.py
absum/absum.py
absum-0.2.3.dist-info/LICENSE
absum-0.2.3.dist-info/METADATA
absum-0.2.3.dist-info/WHEEL
absum-0.2.3.dist-info/top_level.txt
absum-0.2.3.dist-info/RECORD
