Metadata-Version: 2.1
Name: absum
Version: 0.2.3
Summary: Abstractive Summarization for Data Augmentation
Home-page: https://github.com/aaronbriel/absum
Author: Aaron Briel
Author-email: aaronbriel@gmail.com
License: Apache License 2.0
Platform: UNKNOWN
License-File: LICENSE
Requires-Dist: numpy
Requires-Dist: pandas
Requires-Dist: torch
Requires-Dist: transformers
